{"commitInfo":{"timestamp":1776949069033,"operation":"WRITE","operationParameters":{"mode":"Append","partitionBy":"[]"},"readVersion":161,"isolationLevel":"Serializable","isBlindAppend":true,"operationMetrics":{"numFiles":"2","numOutputRows":"1","numOutputBytes":"3405"},"engineInfo":"Apache-Spark/4.1.1 Delta-Lake/4.2.0","txnId":"35e290df-c919-4e16-b54a-5aae4cdfa92c"}}
{"add":{"path":"part-00011-70f17891-8444-4ebe-af3e-cf5ddf6a02af-c000.snappy.parquet","partitionValues":{},"size":2545,"modificationTime":1776949069018,"dataChange":true,"stats":"{\"numRecords\":1,\"minValues\":{\"alert_id\":\"350be953-f5ec-4a08-bfac-ba7b2ada\",\"transaction_id\":\"fb79435f-2005-465f-9986-6b29eb8b\",\"user_id\":\"user_29510\",\"alert_type\":\"HIGH_AMOUNT\",\"severity\":\"HIGH\",\"timestamp\":\"2026-04-23T14:57:48.235+02:00\"},\"maxValues\":{\"alert_id\":\"350be953-f5ec-4a08-bfac-ba7b2ada\",\"transaction_id\":\"fb79435f-2005-465f-9986-6b29eb8b\",\"user_id\":\"user_29510\",\"alert_type\":\"HIGH_AMOUNT\",\"severity\":\"HIGH\",\"timestamp\":\"2026-04-23T14:57:48.235+02:00\"},\"nullCount\":{\"alert_id\":0,\"transaction_id\":0,\"user_id\":0,\"alert_type\":0,\"severity\":0,\"amount\":1,\"timestamp\":0}}"}}
