{"commitInfo":{"timestamp":1776950436099,"operation":"WRITE","operationParameters":{"mode":"Append","partitionBy":"[]"},"readVersion":297,"isolationLevel":"Serializable","isBlindAppend":true,"operationMetrics":{"numFiles":"2","numOutputRows":"1","numOutputBytes":"3497"},"engineInfo":"Apache-Spark/4.1.1 Delta-Lake/4.2.0","txnId":"94d545d8-797c-447c-ac2b-a4f1187cc7c3"}}
{"add":{"path":"part-00011-55de30a9-4a0b-471a-b4da-c8b156dc55b0-c000.snappy.parquet","partitionValues":{},"size":2637,"modificationTime":1776950435895,"dataChange":true,"stats":"{\"numRecords\":1,\"minValues\":{\"alert_id\":\"2486ba99-f6c3-4996-be0d-2330766d\",\"transaction_id\":\"966e5d70-19d6-4f2a-ab48-31c2f73f\",\"user_id\":\"user_27880\",\"alert_type\":\"HIGH_AMOUNT\",\"severity\":\"CRITICAL\",\"amount\":0.0,\"timestamp\":\"2026-04-23T15:20:34.975+02:00\"},\"maxValues\":{\"alert_id\":\"2486ba99-f6c3-4996-be0d-2330766d\",\"transaction_id\":\"966e5d70-19d6-4f2a-ab48-31c2f73f\",\"user_id\":\"user_27880\",\"alert_type\":\"HIGH_AMOUNT\",\"severity\":\"CRITICAL\",\"amount\":0.0,\"timestamp\":\"2026-04-23T15:20:34.975+02:00\"},\"nullCount\":{\"alert_id\":0,\"transaction_id\":0,\"user_id\":0,\"alert_type\":0,\"severity\":0,\"amount\":0,\"timestamp\":0}}"}}
