{"commitInfo":{"timestamp":1776949767035,"operation":"WRITE","operationParameters":{"mode":"Append","partitionBy":"[]"},"readVersion":238,"isolationLevel":"Serializable","isBlindAppend":true,"operationMetrics":{"numFiles":"2","numOutputRows":"1","numOutputBytes":"3426"},"engineInfo":"Apache-Spark/4.1.1 Delta-Lake/4.2.0","txnId":"abfd2124-4328-438c-86c4-ed9d9094ffad"}}
{"add":{"path":"part-00011-08a81edb-13ab-4e8d-ab39-91b537b2662f-c000.snappy.parquet","partitionValues":{},"size":2566,"modificationTime":1776949766994,"dataChange":true,"stats":"{\"numRecords\":1,\"minValues\":{\"alert_id\":\"67cb9c8b-7d57-4945-ac0c-fe3981db\",\"transaction_id\":\"eaa33af4-8f3c-4d29-b143-5394b07a\",\"user_id\":\"user_8439\",\"alert_type\":\"HIGH_AMOUNT\",\"severity\":\"CRITICAL\",\"timestamp\":\"2026-04-23T15:09:26.353+02:00\"},\"maxValues\":{\"alert_id\":\"67cb9c8b-7d57-4945-ac0c-fe3981db\",\"transaction_id\":\"eaa33af4-8f3c-4d29-b143-5394b07a\",\"user_id\":\"user_8439\",\"alert_type\":\"HIGH_AMOUNT\",\"severity\":\"CRITICAL\",\"timestamp\":\"2026-04-23T15:09:26.353+02:00\"},\"nullCount\":{\"alert_id\":0,\"transaction_id\":0,\"user_id\":0,\"alert_type\":0,\"severity\":0,\"amount\":1,\"timestamp\":0}}"}}
